chiptune/__init__.py
chiptune/cli.py
chiptune/presets.py
chiptune/chip/__init__.py
chiptune/chip/channels.py
chiptune/chip/effects.py
chiptune/chip/systems/__init__.py
chiptune/chip/systems/base.py
chiptune/chip/systems/gameboy.py
chiptune/chip/systems/genesis.py
chiptune/chip/systems/nes.py
chiptune/chip/systems/sid.py
chiptune/composer/__init__.py
chiptune/composer/agent_api.py
chiptune/composer/composer.py
chiptune/generation/__init__.py
chiptune/generation/adaptive/__init__.py
chiptune/generation/adaptive/intensity.py
chiptune/generation/harmony/__init__.py
chiptune/generation/harmony/bass.py
chiptune/generation/harmony/countermelody.py
chiptune/generation/markov/__init__.py
chiptune/generation/markov/chain.py
chiptune/generation/markov/melody.py
chiptune/output/__init__.py
chiptune/output/midi.py
chiptune/output/audio/__init__.py
chiptune/output/audio/envelope.py
chiptune/output/audio/exporter.py
chiptune/output/audio/mixer.py
chiptune/output/audio/playback.py
chiptune/output/audio/waveforms.py
chiptune/output/audio/effects/__init__.py
chiptune/output/audio/effects/base.py
chiptune/output/audio/effects/chain.py
chiptune/output/audio/effects/chorus.py
chiptune/output/audio/effects/echo.py
chiptune/output/audio/effects/lfo.py
chiptune/output/audio/effects/pitch_sweep.py
chiptune/output/audio/effects/tape_delay.py
chiptune/output/audio/effects/tremolo.py
chiptune/output/audio/effects/vibrato.py
chiptune/patterns/__init__.py
chiptune/patterns/jingles.py
chiptune/patterns/progressions.py
chiptune/patterns/themes.py
chiptune/sfx/__init__.py
chiptune/sfx/effects.py
chiptune/theory/__init__.py
chiptune/theory/arpeggios.py
chiptune/theory/chords.py
chiptune/theory/keys.py
chiptune/theory/scales.py
flexinfer_chiptune-0.5.2.dist-info/METADATA
flexinfer_chiptune-0.5.2.dist-info/WHEEL
flexinfer_chiptune-0.5.2.dist-info/entry_points.txt
flexinfer_chiptune-0.5.2.dist-info/RECORD
