Metadata-Version: 2.4
Name: flexinfer-chiptune
Version: 0.5.2
Summary: Retro game music generation library with semantic API for 8-bit/16-bit style MIDI and audio composition
Author-email: Cody Blevins <cody@flexinfer.ai>
License: MIT
Classifier: Operating System :: OS Independent
Classifier: Programming Language :: Python :: 3
Classifier: Programming Language :: Python :: 3.11
Classifier: Programming Language :: Python :: 3.12
Classifier: Topic :: Artistic Software
Classifier: Topic :: Multimedia :: Sound/Audio :: MIDI
Requires-Python: >=3.11
Requires-Dist: midiutil>=1.2.1
Requires-Dist: music21>=9.0.0
Requires-Dist: numpy>=1.20.0
Requires-Dist: pydantic>=2.0.0
Requires-Dist: scipy>=1.10.0
Requires-Dist: soundfile>=0.12.0
Provides-Extra: audio
Requires-Dist: sounddevice>=0.4.6; extra == 'audio'
Provides-Extra: dev
Requires-Dist: mypy>=1.0.0; extra == 'dev'
Requires-Dist: pre-commit>=3.5.0; extra == 'dev'
Requires-Dist: pytest-cov>=4.0.0; extra == 'dev'
Requires-Dist: pytest>=7.0.0; extra == 'dev'
Requires-Dist: ruff>=0.1.0; extra == 'dev'
Requires-Dist: sounddevice>=0.4.6; extra == 'dev'
